{"telemetry_id":"8wic76we536pz4hi","slug":"starwars-data-modeling","agent":"vscode","tutorial_started_at":1724818822000,"steps":[{"slug":"assets","position":0,"files":[{"path":"assets/example.png","name":"example.png","hidden":true},{"path":"assets/preview.png","name":"preview.png","hidden":true}],"ai_interactions":[],"compilations":[],"tests":[],"is_testeable":false},{"slug":"src","position":1,"files":[{"path":"src/models.py","name":"models.py","hidden":false}],"ai_interactions":[],"compilations":[],"tests":[],"is_testeable":false}],"workout_session":[{"started_at":1724818822000}]}